netorchestr/__init__.py
netorchestr/cmdenv/__init__.py
netorchestr/common/__init__.py
netorchestr/common/util/__init__.py
netorchestr/common/util/dataAnalysis.py
netorchestr/common/util/dataGen.py
netorchestr/common/util/jsonRead.py
netorchestr/common/util/runCommand.py
netorchestr/envir/__init__.py
netorchestr/envir/applications/__init__.py
netorchestr/envir/applications/simple.py
netorchestr/envir/applications/ueapp.py
netorchestr/envir/applications/vnfapp.py
netorchestr/envir/base/__init__.py
netorchestr/envir/base/ogate.py
netorchestr/envir/base/olink.py
netorchestr/envir/base/omessage.py
netorchestr/envir/base/omodule.py
netorchestr/envir/base/onet.py
netorchestr/envir/clock/__init__.py
netorchestr/envir/clock/timer.py
netorchestr/envir/linklayer/__init__.py
netorchestr/envir/mobility/__init__.py
netorchestr/envir/mobility/base.py
netorchestr/envir/mobility/pedestrian.py
netorchestr/envir/mobility/space.py
netorchestr/envir/mobility/traj.py
netorchestr/envir/networklayer/__init__.py
netorchestr/envir/networklayer/base.py
netorchestr/envir/node/__init__.py
netorchestr/envir/node/base.py
netorchestr/envir/node/container.py
netorchestr/envir/node/ground.py
netorchestr/envir/node/laser.py
netorchestr/envir/node/oran.py
netorchestr/envir/node/pedestrian.py
netorchestr/envir/node/satellite.py
netorchestr/envir/node/switch.py
netorchestr/envir/node/uav.py
netorchestr/envir/node/ue.py
netorchestr/envir/node/controller/__init__.py
netorchestr/envir/node/controller/controller4crowd.py
netorchestr/envir/node/controller/controller4ue.py
netorchestr/envir/node/controller/mano/__init__.py
netorchestr/envir/node/controller/mano/mano.py
netorchestr/envir/node/controller/mano/nfvo.py
netorchestr/envir/node/controller/mano/trace.py
netorchestr/envir/node/controller/mano/uem.py
netorchestr/envir/node/controller/mano/vim.py
netorchestr/envir/node/controller/mano/vnfm.py
netorchestr/envir/node/controller/mano/solver_deploy/__init__.py
netorchestr-0.1.1.dist-info/licenses/LICENSE
netorchestr-0.1.1.dist-info/METADATA
netorchestr-0.1.1.dist-info/WHEEL
netorchestr-0.1.1.dist-info/top_level.txt
netorchestr-0.1.1.dist-info/RECORD
