Metadata-Version: 2.4
Name: NetOrchestr
Version: 0.1.1
Summary: A network emulator for network orchestration and automation
Author-email: WangXi <wangxi_chn@foxmail.com>
License-Expression: GPL-3.0
Project-URL: Homepage, https://gitee.com/WangXi_Chn/netorchestr
Requires-Python: >=3.10
License-File: LICENSE
Dynamic: license-file
